lightfm/__init__.py
lightfm/_lightfm_fast.py
lightfm/_lightfm_fast_no_openmp.c
lightfm/_lightfm_fast_no_openmp.cpython-39-darwin.so
lightfm/_lightfm_fast_openmp.c
lightfm/cross_validation.py
lightfm/data.py
lightfm/evaluation.py
lightfm/lightfm.py
lightfm/version.py
lightfm/datasets/__init__.py
lightfm/datasets/_common.py
lightfm/datasets/movielens.py
lightfm/datasets/stackexchange.py
rectools_lightfm-1.17.3.dist-info/LICENSE
rectools_lightfm-1.17.3.dist-info/METADATA
rectools_lightfm-1.17.3.dist-info/WHEEL
rectools_lightfm-1.17.3.dist-info/top_level.txt
rectools_lightfm-1.17.3.dist-info/RECORD
