Metadata-Version: 2.1
Name: rectools-lightfm
Version: 1.17.3
Summary: LightFM recommendation model
Home-page: https://github.com/feldlime/rectools-lightfm
Download-URL: https://github.com/feldlime/rectools-lightfm/tarball/1.17.3
Author: Lyst Ltd (Maciej Kula)
Author-email: feldlime@gmail.com
License: MIT
Classifier: Development Status :: 5 - Production/Stable
Classifier: License :: OSI Approved :: MIT License
Classifier: Topic :: Scientific/Engineering :: Artificial Intelligence
License-File: LICENSE
Requires-Dist: numpy
Requires-Dist: scipy (>=0.17.0)
Requires-Dist: requests
Requires-Dist: scikit-learn
